{
  "ultima_atualizacao": "16/06/2026 13:58",
  "meses": {
    "jan/26": {
      "mes": "jan/26",
      "CMM": 409644.81,
      "FM": 0.5,
      "Nf": 0,
      "Ni": 0,
      "Pt": 0,
      "NCEi": 0,
      "NCEa": 0,
      "NCNEi": 29,
      "NCNEa": 29,
      "Dm": 31,
      "Ti": 0,
      "pOtimo": 53.8,
      "pBom": 30.8,
      "pReg": 7.7,
      "pRuim": 7.7,
      "lig": 0,
      "nOp": 0
    },
    "fev/26": {
      "mes": "fev/26",
      "CMM": 409644.81,
      "FM": 0.5,
      "Nf": 0,
      "Ni": 0,
      "Pt": 0,
      "NCEi": 0,
      "NCEa": 0,
      "NCNEi": 18,
      "NCNEa": 18,
      "Dm": 28,
      "Ti": 0,
      "pOtimo": 52.9,
      "pBom": 38.2,
      "pReg": 8.8,
      "pRuim": 0,
      "lig": 0,
      "nOp": 0
    },
    "mar/26": {
      "mes": "mar/26",
      "CMM": 409644.81,
      "FM": 0.5,
      "Nf": 20,
      "Ni": 20,
      "Pt": 15788,
      "NCEi": 0,
      "NCEa": 0,
      "NCNEi": 17,
      "NCNEa": 17,
      "Dm": 31,
      "Ti": 0,
      "pOtimo": 76.2,
      "pBom": 14.3,
      "pReg": 4.8,
      "pRuim": 4.8,
      "lig": 0,
      "nOp": 0
    },
    "abr/26": {
      "mes": "abr/26",
      "CMM": 427136.76,
      "FM": 0.5,
      "Nf": 221,
      "Ni": 0,
      "Pt": 15879,
      "NCEi": 2,
      "NCEa": 2,
      "NCNEi": 15,
      "NCNEa": 15,
      "Dm": 30,
      "Ti": 0,
      "pOtimo": 64.0,
      "pBom": 36.0,
      "pReg": 0,
      "pRuim": 0,
      "lig": 26,
      "nOp": 2
    }
  }
}